datetime_event_store/__init__.py
datetime_event_store/event_store.py
datetime_event_store/tests/__init__.py
datetime_event_store/tests/test_event_store.py
ikare_event_store-0.1.0.dist-info/licenses/LICENSE
ikare_event_store-0.1.0.dist-info/METADATA
ikare_event_store-0.1.0.dist-info/WHEEL
ikare_event_store-0.1.0.dist-info/top_level.txt
ikare_event_store-0.1.0.dist-info/RECORD
