Metadata-Version: 2.4
Name: Ikare_event_store
Version: 0.1.0
Summary: Un package pour stocker et récupérer des événements associés à des dates
Author: FETNI Mohamed
Author-email: MFE.FETNI.MOHAMED@GMAIL.COM
Classifier: Programming Language :: Python :: 3
Classifier: License :: OSI Approved :: MIT License
Classifier: Operating System :: OS Independent
Requires-Python: >=3.6
License-File: LICENSE
Dynamic: author
Dynamic: author-email
Dynamic: classifier
Dynamic: license-file
Dynamic: requires-python
Dynamic: summary
